rwkv5_cuda_attention/__init__.py
rwkv5_cuda_attention/rwkv5_cuda_interface.py
rwkv_cuda_attention-0.1.1.dist-info/METADATA
rwkv_cuda_attention-0.1.1.dist-info/WHEEL
rwkv_cuda_attention-0.1.1.dist-info/top_level.txt
rwkv_cuda_attention-0.1.1.dist-info/RECORD
